{
    "id": 61910810,
    "name": "TANTRUM",
    "author": "DanZmeN",
    "creators": ["flash, BlueRimz, DanZmeN, BitZel, SpooFy, ViralDL, Yendis, ItzMezzo"],
    "verifier": "Golden",
    "verification": "https://youtu.be/4iTMCQMGz-U",
    "percentToQualify": "100",
    "password": "Free To Copy",
    "records": [
        {
            "user": "gamecheese",
            "link": "https://youtu.be/NaihMjhqbA8?si=lHNr7oJ7DKfPMPVq",
            "percent": 100,
            "hz": 144
        }
    ]
}
